monailabel/__init__.py
monailabel/_version.py
monailabel/app.py
monailabel/config.py
monailabel/logging.json
monailabel/main.py
monailabel/client/__init__.py
monailabel/client/client.py
monailabel/datastore/__init__.py
monailabel/datastore/cvat.py
monailabel/datastore/dicom.py
monailabel/datastore/dsa.py
monailabel/datastore/local.py
monailabel/datastore/xnat.py
monailabel/datastore/utils/__init__.py
monailabel/datastore/utils/colors.py
monailabel/datastore/utils/convert.py
monailabel/datastore/utils/dicom.py
monailabel/deepedit/__init__.py
monailabel/deepedit/handlers.py
monailabel/deepedit/interaction.py
monailabel/deepedit/transforms.py
monailabel/endpoints/__init__.py
monailabel/endpoints/activelearning.py
monailabel/endpoints/batch_infer.py
monailabel/endpoints/datastore.py
monailabel/endpoints/infer.py
monailabel/endpoints/info.py
monailabel/endpoints/login.py
monailabel/endpoints/logs.py
monailabel/endpoints/model.py
monailabel/endpoints/ohif.py
monailabel/endpoints/proxy.py
monailabel/endpoints/scoring.py
monailabel/endpoints/session.py
monailabel/endpoints/train.py
monailabel/endpoints/wsi_infer.py
monailabel/endpoints/static/.gitignore
monailabel/endpoints/static/favicon.ico
monailabel/endpoints/user/__init__.py
monailabel/endpoints/user/auth.py
monailabel/interfaces/__init__.py
monailabel/interfaces/app.py
monailabel/interfaces/config.py
monailabel/interfaces/datastore.py
monailabel/interfaces/exception.py
monailabel/interfaces/tasks/__init__.py
monailabel/interfaces/tasks/batch_infer.py
monailabel/interfaces/tasks/infer.py
monailabel/interfaces/tasks/infer_v2.py
monailabel/interfaces/tasks/scoring.py
monailabel/interfaces/tasks/strategy.py
monailabel/interfaces/tasks/train.py
monailabel/interfaces/utils/__init__.py
monailabel/interfaces/utils/app.py
monailabel/interfaces/utils/transform.py
monailabel/interfaces/utils/wsi.py
monailabel/scribbles/__init__.py
monailabel/scribbles/infer.py
monailabel/scribbles/transforms.py
monailabel/scribbles/utils.py
monailabel_weekly-0.5.dev2308.dist-info/LICENSE
monailabel_weekly-0.5.dev2308.dist-info/METADATA
monailabel_weekly-0.5.dev2308.dist-info/WHEEL
monailabel_weekly-0.5.dev2308.dist-info/top_level.txt
monailabel_weekly-0.5.dev2308.dist-info/RECORD
