Metadata-Version: 2.1
Name: monailabel-weekly
Version: 0.5.dev2308
Summary: Active Learning Toolkit for Healthcare Imaging
Home-page: https://monai.io/
Author: MONAI Consortium
Author-email: monai.contact@gmail.com
License: Apache License 2.0
Project-URL: Documentation, https://docs.monai.io/
Project-URL: Bug Tracker, https://github.com/Project-MONAI/MONAILabel/issues
Project-URL: Source Code, https://github.com/Project-MONAI/MONAILabel
Platform: OS Independent
Requires-Python: >=3.7
License-File: LICENSE
Requires-Dist: torch (>=1.7)
Requires-Dist: monai[fire,gdown,ignite,itk,lmdb,mlflow,nibabel,openslide,pillow,psutil,skimage,tensorboard,torchvision,tqdm] (>=1.1.0)
Requires-Dist: uvicorn (==0.17.6)
Requires-Dist: pydantic (>=1.8.2)
Requires-Dist: python-dotenv (==0.20.0)
Requires-Dist: fastapi (==0.78.0)
Requires-Dist: python-multipart (==0.0.5)
Requires-Dist: requests-toolbelt (==0.9.1)
Requires-Dist: httpx (==0.23.0)
Requires-Dist: schedule (==1.1.0)
Requires-Dist: dicomweb-client (==0.56.2)
Requires-Dist: timeloop (==1.0.2)
Requires-Dist: expiringdict (==1.2.1)
Requires-Dist: expiring-dict (==1.1.0)
Requires-Dist: cachetools (==5.2.0)
Requires-Dist: watchdog (==2.1.8)
Requires-Dist: pydicom (==2.3.0)
Requires-Dist: pydicom-seg (==0.4.0)
Requires-Dist: pynetdicom (==2.0.2)
Requires-Dist: pynrrd (==0.4.3)
Requires-Dist: opencv-python-headless (==4.5.5.64)
Requires-Dist: numpymaxflow (==0.0.5)
Requires-Dist: girder-client (==3.1.14)
Requires-Dist: ninja (==1.10.2.3)
Requires-Dist: einops (>=0.3.2)
Requires-Dist: PyYAML (==6.0)
Requires-Dist: filelock (==3.7.1)
Requires-Dist: passlib (==1.7.4)
Requires-Dist: python-jose[cryptography] (==3.3.0)
Requires-Dist: bcrypt (==3.2.2)
Requires-Dist: shapely (==1.8.2)
Requires-Dist: requests (==2.28.1)
Requires-Dist: scikit-learn
Requires-Dist: scipy
Requires-Dist: itk (>=5.3rc4.post3) ; python_version == "3.10"
